ormlet/__init__.py
ormlet/column.py
ormlet/manager.py
ormlet/model.py
ormlet/query_builder.py
ormlet/result_map.py
ormlet-0.1.0.dist-info/METADATA
ormlet-0.1.0.dist-info/WHEEL
ormlet-0.1.0.dist-info/top_level.txt
ormlet-0.1.0.dist-info/RECORD
