Metadata-Version: 2.4
Name: ormlet
Version: 0.1.0
Summary: Ormlet is a lightweight, minimal ORM designed to give you just enough structure and flexibility to build SQL queries.
Project-URL: Homepage, https://github.com/chamanbravo/ormlet
Project-URL: Repository, https://github.com/chamanbravo/ormlet
Project-URL: Issues, https://github.com/chamanbravo/ormlet/issues
Classifier: Intended Audience :: Information Technology
Classifier: Intended Audience :: System Administrators
Classifier: Operating System :: OS Independent
Classifier: Programming Language :: Python :: 3
Classifier: Programming Language :: Python
Classifier: Topic :: Software Development :: Libraries :: Application Frameworks
Classifier: Topic :: Software Development :: Libraries :: Python Modules
Classifier: Topic :: Software Development :: Libraries
Classifier: Topic :: Software Development
Classifier: Typing :: Typed
Classifier: Intended Audience :: Developers
Classifier: License :: OSI Approved :: MIT License
Requires-Python: >=3.13
